{
  "pmid": "1697648",
  "title": "Identification of the 64K autoantigen in insulin-dependent diabetes as the GABA-synthesizing enzyme glutamic acid decarboxylase.",
  "abstract": "The pancreatic islet beta-cell autoantigen of relative molecular mass 64,000 (64K), which is a major target of autoantibodies associated with the development of insulin-dependent diabetes mellitus (IDDM) has been identified as glutamic acid decarboxylase, the biosynthesizing enzyme of the inhibitory neurotransmitter GABA (gamma-aminobutyric acid). Pancreatic beta cells and a subpopulation of central nervous system neurons express high levels of this enzyme. Autoantibodies against glutamic acid decarboxylase with a higher titre and increased epitope recognition compared with those usually associated with IDDM are found in stiff-man syndrome, a rare neurological disorder characterized by a high coincidence with IDDM.",
  "keywords": [],
  "mesh_terms": [
    "Animals",
    "Animals, Newborn",
    "Autoantibodies",
    "Autoantigens",
    "Autoimmunity",
    "Brain",
    "Diabetes Mellitus, Experimental",
    "Diabetes Mellitus, Type 1",
    "Epitopes",
    "Glutamate Decarboxylase",
    "Immunosorbent Techniques",
    "Islets of Langerhans",
    "Molecular Weight",
    "Nervous System Diseases",
    "Rats",
    "Syndrome",
    "gamma-Aminobutyric Acid"
  ],
  "pub_types": [
    "Journal Article",
    "Research Support, Non-U.S. Gov't",
    "Research Support, U.S. Gov't, P.H.S."
  ],
  "doi": "10.1038/347151a0",
  "journal": "Nature",
  "year": "1990",
  "authors": [
    "Baekkeskov S",
    "Aanstoot H",
    "Christgau S",
    "Reetz A",
    "Solimena M",
    "Cascalho M",
    "Folli F",
    "Richter-Olesen H",
    "De Camilli P"
  ],
  "cited_pmids": [],
  "fetched_at": "2026-03-17T00:21:12.972488"
}